{
  "": "",
  "Ваш аватар": "",
  "Ваш возраст": "",
  "Ваш город": "",
  "Ваша страна": "",
  "Ваша фамилия": "Ваша фамилия",
  "Ваше имя": "",
  "Ваше логин": "",
  "Введите имя пользователя": "",
  "Введите ссылку на аватар": "",
  "Возраст": "",
  "Город": "",
  "Данные не указаны": "",
  "Имя": "",
  "Имя и фамилия обязательны": "",
  "Имя пользователя": "",
  "Некорректная страна": "",
  "Некорректный возраст": "",
  "Некорректный регион": "",
  "Нет данных": "",
  "Отменить": "",
  "Ошибка в имени или фамилии": "",
  "Попробуйте ": "",
  "Попробуйте обновить ошибку": "",
  "Попробуйте обновить страницу": "",
  "Произошла ошибка при ": "",
  "Произошла ошибка при загрузке профиля": "",
  "Произошла ошибка при загрузки профиля": "",
  "Профиль": "",
  "Профиль не найден": "Профиль не найден",
  "Редактировать": "",
  "Серверная ошибка при сохранении": "",
  "Сохранить": "",
  "Ссылка на аватар": "",
  "Фамилия": ""
}
